dantico/__init__.py
dantico/exceptions.py
dantico/factory.py
dantico/fields.py
dantico/getters.py
dantico/mixins.py
dantico/model_schema.py
dantico/model_validators.py
dantico/py.typed
dantico/schema.py
dantico/schema_registry.py
dantico/utils.py
dantico-0.0.10.dist-info/METADATA
dantico-0.0.10.dist-info/WHEEL
dantico-0.0.10.dist-info/licenses/LICENSE
dantico-0.0.10.dist-info/RECORD
