Metadata-Version: 2.1
Name: dantico
Version: 0.0.10
Summary: Tools to convert Django ORM models to Pydantic models
Project-URL: Homepage, https://github.com/xshapira/dantico
Project-URL: Documentation, https://github.com/xshapira/dantico
Author-email: Max Shapira <max@winoutt.com>
License-File: LICENSE
Classifier: Environment :: Web Environment
Classifier: Framework :: AsyncIO
Classifier: Framework :: Django
Classifier: Framework :: Django :: 3.0
Classifier: Framework :: Django :: 3.1
Classifier: Framework :: Django :: 3.2
Classifier: Framework :: Django :: 4.0
Classifier: Framework :: Django :: 4.1
Classifier: Intended Audience :: Developers
Classifier: Intended Audience :: Information Technology
Classifier: Intended Audience :: System Administrators
Classifier: License :: OSI Approved :: MIT License
Classifier: Operating System :: OS Independent
Classifier: Programming Language :: Python :: 3 :: Only
Classifier: Programming Language :: Python :: 3.7
Classifier: Programming Language :: Python :: 3.8
Classifier: Programming Language :: Python :: 3.9
Classifier: Programming Language :: Python :: 3.10
Classifier: Programming Language :: Python :: 3.11
Classifier: Topic :: Internet
Classifier: Topic :: Internet :: WWW/HTTP
Classifier: Topic :: Internet :: WWW/HTTP :: HTTP Servers
Classifier: Topic :: Software Development
Classifier: Topic :: Software Development :: Libraries
Classifier: Topic :: Software Development :: Libraries :: Application Frameworks
Classifier: Topic :: Software Development :: Libraries :: Python Modules
Classifier: Typing :: Typed
Requires-Python: >=3.7
Requires-Dist: django>=3.0
Requires-Dist: pydantic
Requires-Dist: pydantic[email]
Provides-Extra: doc
Provides-Extra: test
Requires-Dist: black; extra == 'test'
Requires-Dist: django-stubs[compatible-mypy]; extra == 'test'
Requires-Dist: flake8; extra == 'test'
Requires-Dist: isort; extra == 'test'
Requires-Dist: mypy; extra == 'test'
Requires-Dist: psycopg2-binary; extra == 'test'
Requires-Dist: pytest; extra == 'test'
Requires-Dist: pytest-asyncio; extra == 'test'
Requires-Dist: pytest-cov; extra == 'test'
Requires-Dist: pytest-django; extra == 'test'
